odoo/addons/fieldservice_location_builder/README.rst
odoo/addons/fieldservice_location_builder/__init__.py
odoo/addons/fieldservice_location_builder/__manifest__.py
odoo/addons/fieldservice_location_builder/i18n/de.po
odoo/addons/fieldservice_location_builder/i18n/es.po
odoo/addons/fieldservice_location_builder/i18n/es_CL.po
odoo/addons/fieldservice_location_builder/i18n/fieldservice_location_builder.pot
odoo/addons/fieldservice_location_builder/i18n/pt_BR.po
odoo/addons/fieldservice_location_builder/models/__init__.py
odoo/addons/fieldservice_location_builder/models/fsm_location_level.py
odoo/addons/fieldservice_location_builder/readme/CONTRIBUTORS.rst
odoo/addons/fieldservice_location_builder/readme/DESCRIPTION.rst
odoo/addons/fieldservice_location_builder/readme/ROADMAP.rst
odoo/addons/fieldservice_location_builder/readme/USAGE.rst
odoo/addons/fieldservice_location_builder/static/description/icon.png
odoo/addons/fieldservice_location_builder/static/description/index.html
odoo/addons/fieldservice_location_builder/views/fsm_location_level.xml
odoo/addons/fieldservice_location_builder/wizard/__init__.py
odoo/addons/fieldservice_location_builder/wizard/fsm_location_builder_wizard.py
odoo/addons/fieldservice_location_builder/wizard/fsm_location_builder_wizard.xml
odoo12_addon_fieldservice_location_builder-12.0.1.1.0.dist-info/METADATA
odoo12_addon_fieldservice_location_builder-12.0.1.1.0.dist-info/WHEEL
odoo12_addon_fieldservice_location_builder-12.0.1.1.0.dist-info/top_level.txt
odoo12_addon_fieldservice_location_builder-12.0.1.1.0.dist-info/RECORD
